latkerlo_jvotci-2.4.0.dist-info/METADATA
latkerlo_jvotci-2.4.0.dist-info/WHEEL
latkerlo_jvotci-2.4.0.dist-info/entry_points.txt
latkerlo_jvotci-2.4.0.dist-info/licenses/LICENSE.md
latkerlo_jvotci/.DS_Store
latkerlo_jvotci/.idea/.gitignore
latkerlo_jvotci/.idea/inspectionProfiles/profiles_settings.xml
latkerlo_jvotci/.idea/latkerlo_jvotci.iml
latkerlo_jvotci/.idea/misc.xml
latkerlo_jvotci/.idea/modules.xml
latkerlo_jvotci/.idea/vcs.xml
latkerlo_jvotci/.idea/workspace.xml
latkerlo_jvotci/__init__.py
latkerlo_jvotci/data.py
latkerlo_jvotci/exceptions.py
latkerlo_jvotci/jvozba.py
latkerlo_jvotci/katna.py
latkerlo_jvotci/rafsi.py
latkerlo_jvotci/tarmi.py
latkerlo_jvotci/tools.py
latkerlo_jvotci-2.4.0.dist-info/RECORD
