Metadata-Version: 2.1
Name: latkerlo_jvotci
Version: 2.4.0
Summary: Tools for creating and decomposing lojban lujvo.
Author-Email: latkerlo <latkerlo@latkerlo.com>
License: # License Information
Classifier: License :: OSI Approved :: MIT License
Classifier: Programming Language :: Python :: 3
Classifier: Programming Language :: Python :: 3.10
Classifier: Programming Language :: Python :: 3.11
Classifier: Programming Language :: Python :: 3.12
Project-URL: Repository, https://github.com/latkerlo/latkerlo-jvotci
Requires-Python: >=3.10
